{"4oqZ0CH3I6ek+2Uo3QTkxQ==":"slide3-1600x900.jpg","HpeiD0V9OWKNZHNzeqPjog==":"slide1-1024x576.jpg","92Izoukt/VK+/VWTg0dKfQ==":"slide3-1024x576.jpg","LfwQ0vp6IKDkuEWUCBI9bg==":"whatsapp%20image%202022-12-02%20at%2010.18.24-1600x900.jpg","1PHnfaPaMYDCKKMGQU3LbQ==":"whatsapp%20image%202022-12-02%20at%2009.49.02%20(1)-1600x1200.jpg","PfZdjyJw4wkeTH4OsLac4A==":"whatsapp%20image%202022-12-02%20at%2009.49.02%20(1)-1600x1200.jpeg","8Xc76t4fzUuga3Wmbemlyg==":"whatsapp%20image%202022-12-02%20at%2009.49.01-1600x1200.jpeg","eE1AOXeb8rvYOTgcRexX3g==":"whatsapp%20image%202022-12-02%20at%2009.49.01%20(1)-1200x1600.jpeg","DyU0SGH5kgR6L11sQBGFWA==":"whatsapp%20image%202022-12-02%20at%2010.15.32-1024x768.jpeg","Ny6HkSA4jIwP3k63ar+A2Q==":"whatsapp%20image%202022-12-02%20at%2010.21.20-1600x1200.jpg","H6AuAofZYbpticCFDMs/UQ==":"bg3-1280x854.jpg","uep9dY96SoFi4Q9FActEzg==":"img8-619x348.jpg","eWSoDTK5xwYLr4OY62vvxA==":"img1-619x619.jpg","UUXB4wVoNlalEBmDWst9VQ==":"nature-background-green-foliage-bamboo-leaves-with-bokeh-sunlight-1302x869.jpg","DjuE6A2PyovoNVh7G5dwgw==":"dsc-22-619x413.jpg","uj4JGBPnzBtMUYo/O/f99A==":"logo-manbaulhuda-96x94.png","nnrXMMd9trqnbke2ZSeJ1A==":"slide2-1-1600x900.jpg","JeT0iBExrlNhcVgxA6Xe1A==":"slide2-1-1024x576.jpg","DQ0oQtibPEo/Y726VgkbPA==":"slide1-2-1600x900.jpg","kEFKoOaiunUrilWaKrpRlA==":"slide2-640x360.jpg","nA0fGR/fXygbA13OCVa9yw==":"slide2-1-1600x1080.jpg","YkPw1YJh1JMx1VOhHH+qaA==":"slide1-5-1600x1080.jpg","arP17/gUZZlIkOxw9GUoKg==":"slide3-5-1600x1080.jpg","k9BSvyJCG+TgWeAvMNrcpA==":"frame1-1000.jpg","XfzbMoEkt/7hNxbsFzYQ3w==":"futsal-1440x1440.jpg","F1vpnparqolOj+fJWjLLJA==":"futsal-1440x1070.jpg","y+x31F0SjccnYlszDKupIQ==":"poster-futsal-586x586.jpg","Y4OdS11YkbiujKZdFNwrAQ==":"poster-basket-647x647.jpg","J2pVN3HGMe5a+T+VEdbLBA==":"poster-basket-1-647x647.jpg","Fp3UwSvF6P3UrhoXoupDXg==":"poster-archery-600x600.jpg","yptdULdfvOqA/bV1amBlQQ==":"poster-english-577x577.jpg","l3hxYFONestAygs4/Vvoow==":"04-1.jpg","BTogvuLxRogl97M3AL3l9A==":"03-1.jpg","BBHrC6UPQmcnthvMs/Uhfw==":"poster-badminton-577x577.jpg","SXwYOrF0sTrnb752NB3ECQ==":"poster-renang-577x577.jpg","SNZzvNeG6rJQiSV5wnjjwA==":"poster-tataboga-577x577.jpg","RT1w4xabhVTTyjvBlF5c4Q==":"poster-esport-577x577.jpg","iyP5yUCsatKoxD4x2XM1nQ==":"poster-shurulkhan-577x577.jpg","JyeJKzaqAjhuisiWymk5QA==":"tahfizh-1080x608.jpg","HGIqR1jVa12aBOSxzMEinw==":"mi-mh-1024x768.jpg","n7UWEa6BUoGrDVAEiAlsdg==":"mts-mh-1024x683.jpg","bOpq7JCBF64ZnUMUtUIoMQ==":"mts-mh-min-2000x1333.jpg","IsIWm0w+y2pmQ9SGqOjJkA==":"masanda-min-2000x1200.png","xK1pdZT7yWkasaqJd+2djA==":"mi-mh-desain-min-1280x1145.jpg","NzmHRUZk/OKwgFDh/oqBBQ==":"mts-mh-desain-min-960x660.jpg","21ZmeDn6yP2/XKhA7SEUQg==":"lab-komputer-619x426.jpg","ZejLY80aeiw63vPldayPAA==":"masjid-680x510.jpg","NaX1AaQaP/7JIGk6g0GTow==":"lab-619x619.jpg","OZGtJ4oy+u1GZL1/cCXqNQ==":"kelas-1080x810.jpg"}